fiction_vs_fact/__init__.py
fiction_vs_fact/main.py
fiction_vs_fact/prompts.py
fiction_vs_fact-2025.12.21083650.dist-info/METADATA
fiction_vs_fact-2025.12.21083650.dist-info/WHEEL
fiction_vs_fact-2025.12.21083650.dist-info/top_level.txt
fiction_vs_fact-2025.12.21083650.dist-info/RECORD
